bakcode/__init__.py
bakcode/exceptions.py
bakcode/packer.py
bakcode/revealer.py
bakcode/utils.py
bakcode-1.1.0.dist-info/METADATA
bakcode-1.1.0.dist-info/WHEEL
bakcode-1.1.0.dist-info/entry_points.txt
bakcode-1.1.0.dist-info/top_level.txt
bakcode-1.1.0.dist-info/RECORD
